{
  "build": {
    "configure_args": [],
    "make_args": [],
    "system_kind": "pypi"
  },
  "conflicts": [],
  "dependencies": {
    "build": [
      "setuptools",
      "wheel"
    ],
    "host": [],
    "runtime": [],
    "test": []
  },
  "descriptive": {
    "categories": [
      "python"
    ],
    "homepage": "",
    "license": [
      "MIT"
    ],
    "maintainers": [],
    "summary": "plugin and hook calling mechanisms for python"
  },
  "extensions": {
    "merged_from": [
      "pypi"
    ],
    "pypi": {
      "classifiers": [
        "Development Status :: 6 - Mature",
        "Intended Audience :: Developers",
        "License :: OSI Approved :: MIT License",
        "Operating System :: MacOS :: MacOS X",
        "Operating System :: Microsoft :: Windows",
        "Operating System :: POSIX",
        "Programming Language :: Python :: 3",
        "Programming Language :: Python :: 3 :: Only",
        "Programming Language :: Python :: 3.10",
        "Programming Language :: Python :: 3.11"
      ],
      "requires_python": ">=3.9"
    }
  },
  "features": {},
  "identity": {
    "canonical_id": "pkg:pluggy",
    "canonical_name": "pluggy",
    "ecosystem": "pypi",
    "ecosystem_id": "pluggy",
    "version": "1.6.0"
  },
  "patches": [],
  "platforms": {
    "exclude": [],
    "include": []
  },
  "provenance": {
    "confidence": 0.9,
    "generated_by": "bootstrap_canonical_recipes.py",
    "imported_at": "2026-03-29T19:55:18+00:00",
    "source_path": "https://pypi.org/pypi/pluggy/json",
    "source_repo_commit": null,
    "unmapped": [],
    "warnings": []
  },
  "schema_version": "0.2",
  "sources": [
    {
      "sha256": "7dcc130b76258d33b90f61b658791dede3486c3e6bfb003ee5c9bfb396dd22f3",
      "type": "sdist",
      "url": "https://files.pythonhosted.org/packages/f9/e2/3e91f31a7d2b083fe6ef3fa267035b518369d9511ffab804f839851d2779/pluggy-1.6.0.tar.gz"
    }
  ],
  "tests": {}
}
